{"cameraMode":{"drawMode":0,"name":"Shaded","section":"Shading Mode"},"sceneLighting":true,"audioPlay":false,"sceneViewState":{"m_AlwaysRefresh":false,"showFog":true,"showSkybox":true,"showFlares":true,"showImageEffects":true,"showParticleSystems":true,"showVisualEffectGraphs":true,"m_FxEnabled":true},"in2DMode":false,"pivot":{"x":744.0332641601563,"y":285.0376281738281,"z":324.8778991699219},"rotation":{"x":0.019180571660399438,"y":-0.021570520475506784,"z":-0.0006560548208653927,"w":-0.9996940493583679},"size":528.0,"orthographic":false}